tilly_goodbye.py
tilly_goodbye-0.0.1.dist-info/METADATA
tilly_goodbye-0.0.1.dist-info/WHEEL
tilly_goodbye-0.0.1.dist-info/entry_points.txt
tilly_goodbye-0.0.1.dist-info/top_level.txt
tilly_goodbye-0.0.1.dist-info/RECORD
